nlu_inference/__init__.py
nlu_inference/cli.py
nlu_inference/config.py
nlu_inference/inference.py
nlu_inference/io.py
nlu_inference/language.py
nlu_inference/log_utils_fastapi.py
nlu_inference/tokenizer.py
nlu_inference/utils.py
nlu_inference-0.3.24.dist-info/METADATA
nlu_inference-0.3.24.dist-info/WHEEL
nlu_inference-0.3.24.dist-info/entry_points.txt
nlu_inference-0.3.24.dist-info/RECORD
